malevich_coretools/__init__.py
malevich_coretools/dm_utils.py
malevich_coretools/utils.py
malevich_coretools/abstract/__init__.py
malevich_coretools/abstract/abstract.py
malevich_coretools/abstract/clickhouse.py
malevich_coretools/abstract/operations.py
malevich_coretools/abstract/pipeline.py
malevich_coretools/abstract/statuses.py
malevich_coretools/admin/__init__.py
malevich_coretools/admin/utils.py
malevich_coretools/batch/__init__.py
malevich_coretools/batch/utils.py
malevich_coretools/clickhouse/__init__.py
malevich_coretools/clickhouse/abstract.py
malevich_coretools/clickhouse/query.py
malevich_coretools/clickhouse/utils.py
malevich_coretools/clickhouse/where_utils.py
malevich_coretools/funcs/__init__.py
malevich_coretools/funcs/checks.py
malevich_coretools/funcs/dm_funcs.py
malevich_coretools/funcs/funcs.py
malevich_coretools/funcs/helpers.py
malevich_coretools/secondary/__init__.py
malevich_coretools/secondary/config.py
malevich_coretools/secondary/const.py
malevich_coretools/secondary/helpers.py
malevich_coretools/secondary/kafka_utils.py
malevich_coretools/tools/__init__.py
malevich_coretools/tools/abstract.py
malevich_coretools/tools/vast.py
malevich_coretools-0.3.80.dist-info/licenses/LICENSE
malevich_coretools-0.3.80.dist-info/METADATA
malevich_coretools-0.3.80.dist-info/WHEEL
malevich_coretools-0.3.80.dist-info/top_level.txt
malevich_coretools-0.3.80.dist-info/RECORD
