Metadata-Version: 2.4
Name: malevich-coretools
Version: 0.3.80
Author: Andrew Pogrebnoj
Author-email: andrew@onjulius.co
License-File: LICENSE
Requires-Dist: requests
Requires-Dist: pydantic
Requires-Dist: pandas
Requires-Dist: aiohttp
Requires-Dist: kafka-python
Dynamic: author
Dynamic: author-email
Dynamic: license-file
Dynamic: requires-dist
